jsonQM/__init__.py
jsonQM/model.py
jsonQM/modelserializer.py
jsonQM-0.3.4.dist-info/LICENSE
jsonQM-0.3.4.dist-info/METADATA
jsonQM-0.3.4.dist-info/WHEEL
jsonQM-0.3.4.dist-info/top_level.txt
jsonQM-0.3.4.dist-info/RECORD
