Metadata-Version: 2.1
Name: jsonQM
Version: 0.3.4
Summary: A simple tool to easily make your API endpoint json queries more versatile.
Author: William A. Lim
Author-email: william.lim@csu.fullerton.edu
Project-URL: Source, https://github.com/FrewtyPebbles/jsonQM
Project-URL: Tracker, https://github.com/FrewtyPebbles/jsonQM/issues
Keywords: python,json,request,query,model
Classifier: Programming Language :: Python :: 3
Classifier: Operating System :: OS Independent
License-File: LICENSE
